rtl/mod6_count.v
module mod6_count(
input clk,rst,
output reg [2:0]q
);

always@(posedge clk, posedge rst)
begin
if(rst)
	q <= 4'b000;

else
begin	
if(q == 4'b101)
	q <= 4'b000;
else 
	q <= q+1;
end
end

endmodule

tb/tb_mod6.v
module tb_mod6;
reg clk,rst;
wire [2:0]q;

mod6_count DUT(.clk(clk),.rst(rst),.q(q));

initial begin
rst = 1; clk = 0;
#8 rst = 0;
#120 $finish; 
end

always #5 clk = ~clk;

initial begin
$dumpfile("mod6.vcd");
$dumpvars;
end

endmodule

mod6.vcd
$date
    Dec 20, 2023  15:38:18
$end
$version
    TOOL:	ncsim(64)	15.20-s086
$end
$timescale
    1 ns
$end

$scope module tb_mod6 $end
$var reg       1 !    clk  $end
$var reg       1 "    rst  $end
$var wire      3 #    q [2:0] $end

$scope module DUT $end
$var wire      1 $    clk  $end
$var wire      1 %    rst  $end
$var reg       3 &    q [2:0] $end
$upscope $end

$upscope $end

$enddefinitions $end
$dumpvars
0!
1"
b0 #
0$
1%
b0 &
$end
#5
1!
1$
#8
0"
0%
#10
0!
0$
#15
1!
1$
b1 &
b1 #
#20
0!
0$
#25
1!
1$
b10 &
b10 #
#30
0!
0$
#35
1!
1$
b11 &
b11 #
#40
0!
0$
#45
1!
1$
b100 &
b100 #
#50
0!
0$
#55
1!
1$
b101 &
b101 #
#60
0!
0$
#65
1!
1$
b0 &
b0 #
#70
0!
0$
#75
1!
1$
b1 &
b1 #
#80
0!
0$
#85
1!
1$
b10 &
b10 #
#90
0!
0$
#95
1!
1$
b11 &
b11 #
#100
0!
0$
#105
1!
1$
b100 &
b100 #
#110
0!
0$
#115
1!
1$
b101 &
b101 #
#120
0!
0$
#125
1!
1$
b0 &
b0 #
