mod9_new.v
module mod9_counter(
input clk,rst,
output reg [3:0]q
);

always@(posedge clk)
begin
if(rst)
	q <= 4'b0000;

else
begin	
if(q == 4'b1000)
	q <= 4'b0000;
else 
	q <= q+1;
end
end

endmodule

tb_mod9.v
module tb_mod9;
reg clk,rst;
wire [3:0]q;

mod9_counter DUT(.clk(clk),.rst(rst),.q(q));

initial begin
rst = 1; clk = 0;
#8 rst = 0;
#120 $finish; 
end

always #5 clk = ~clk;

initial begin
$dumpfile("mod9.vcd");
$dumpvars;
end

endmodule

mod9.vcd
$date
    Dec 20, 2023  15:33:49
$end
$version
    TOOL:	ncsim(64)	15.20-s086
$end
$timescale
    1 ns
$end

$scope module tb_mod9 $end
$var reg       1 !    clk  $end
$var reg       1 "    rst  $end
$var wire      4 #    q [3:0] $end

$scope module DUT $end
$var wire      1 $    clk  $end
$var wire      1 %    rst  $end
$var reg       4 &    q [3:0] $end
$upscope $end

$upscope $end

$enddefinitions $end
$dumpvars
0!
1"
bx #
0$
1%
bx &
$end
#5
1!
1$
b0 &
b0 #
#8
0"
0%
#10
0!
0$
#15
1!
1$
b1 &
b1 #
#20
0!
0$
#25
1!
1$
b10 &
b10 #
#30
0!
0$
#35
1!
1$
b11 &
b11 #
#40
0!
0$
#45
1!
1$
b100 &
b100 #
#50
0!
0$
#55
1!
1$
b101 &
b101 #
#60
0!
0$
#65
1!
1$
b110 &
b110 #
#70
0!
0$
#75
1!
1$
b111 &
b111 #
#80
0!
0$
#85
1!
1$
b1000 &
b1000 #
#90
0!
0$
#95
1!
1$
b0 &
b0 #
#100
0!
0$
#105
1!
1$
b1 &
b1 #
#110
0!
0$
#115
1!
1$
b10 &
b10 #
#120
0!
0$
#125
1!
1$
b11 &
b11 #
